github/AccessToken.py
github/AccessToken.pyi
github/ApplicationOAuth.py
github/ApplicationOAuth.pyi
github/AuthenticatedUser.py
github/AuthenticatedUser.pyi
github/Authorization.py
github/Authorization.pyi
github/AuthorizationApplication.py
github/AuthorizationApplication.pyi
github/Branch.py
github/Branch.pyi
github/BranchProtection.py
github/BranchProtection.pyi
github/CheckRun.py
github/CheckRun.pyi
github/CheckRunAnnotation.py
github/CheckRunAnnotation.pyi
github/CheckRunOutput.py
github/CheckRunOutput.pyi
github/CheckSuite.py
github/CheckSuite.pyi
github/Clones.py
github/Clones.pyi
github/Commit.py
github/Commit.pyi
github/CommitCombinedStatus.py
github/CommitCombinedStatus.pyi
github/CommitComment.py
github/CommitComment.pyi
github/CommitStats.py
github/CommitStats.pyi
github/CommitStatus.py
github/CommitStatus.pyi
github/Comparison.py
github/Comparison.pyi
github/Consts.py
github/ContentFile.py
github/ContentFile.pyi
github/Deployment.py
github/Deployment.pyi
github/DeploymentStatus.py
github/DeploymentStatus.pyi
github/Download.py
github/Download.pyi
github/Event.py
github/Event.pyi
github/File.py
github/File.pyi
github/Gist.py
github/Gist.pyi
github/GistComment.py
github/GistComment.pyi
github/GistFile.py
github/GistFile.pyi
github/GistHistoryState.py
github/GistHistoryState.pyi
github/GitAuthor.py
github/GitAuthor.pyi
github/GitBlob.py
github/GitBlob.pyi
github/GitCommit.py
github/GitCommit.pyi
github/GitObject.py
github/GitObject.pyi
github/GitRef.py
github/GitRef.pyi
github/GitRelease.py
github/GitRelease.pyi
github/GitReleaseAsset.py
github/GitReleaseAsset.pyi
github/GitTag.py
github/GitTag.pyi
github/GitTree.py
github/GitTree.pyi
github/GitTreeElement.py
github/GitTreeElement.pyi
github/GithubApp.py
github/GithubApp.pyi
github/GithubException.py
github/GithubException.pyi
github/GithubObject.py
github/GithubObject.pyi
github/GitignoreTemplate.py
github/GitignoreTemplate.pyi
github/Hook.py
github/Hook.pyi
github/HookDescription.py
PyGithubF-1.56.dist-info/COPYING
PyGithubF-1.56.dist-info/COPYING.LESSER
PyGithubF-1.56.dist-info/METADATA
PyGithubF-1.56.dist-info/WHEEL
PyGithubF-1.56.dist-info/top_level.txt
PyGithubF-1.56.dist-info/RECORD
