Metadata-Version: 2.1
Name: PyGithubF
Version: 1.56
Summary: Use the full Github API v3
Home-page: https://github.com/pygithub/pygithub
Author: Ivan Mucyo Ngabo
Author-email: ivanmucyongabo@outlook.com
Project-URL: Documentation, http://pygithub.readthedocs.io/en/latest/
Project-URL: Source, https://github.com/ivanmucyongabo/PyGithubF
Project-URL: Tracker, https://github.com/ivanmucyongabo/PyGithubF/issues
Classifier: Development Status :: 5 - Production/Stable
Classifier: Environment :: Web Environment
Classifier: Intended Audience :: Developers
Classifier: License :: OSI Approved :: GNU Library or Lesser General Public License (LGPL)
Classifier: Operating System :: OS Independent
Classifier: Programming Language :: Python
Classifier: Programming Language :: Python :: 3
Classifier: Programming Language :: Python :: 3.6
Classifier: Programming Language :: Python :: 3.7
Classifier: Programming Language :: Python :: 3.8
Classifier: Programming Language :: Python :: 3.9
Classifier: Programming Language :: Python :: 3.10
Classifier: Topic :: Software Development
Requires-Python: >=3.6
License-File: COPYING
License-File: COPYING.LESSER
Requires-Dist: pynacl (==1.4.0)
Requires-Dist: requests (==2.14.0)
Requires-Dist: pyjwt (==2.0)
Requires-Dist: deprecated (==1.2.13)
Provides-Extra: integrations
Requires-Dist: cryptography (==38.0.1) ; extra == 'integrations'
